README.rst
setup.cfg
setup.py
nap_token/__init__.py
nap_token/middleware.py
nap_token_auth.egg-info/PKG-INFO
nap_token_auth.egg-info/SOURCES.txt
nap_token_auth.egg-info/dependency_links.txt
nap_token_auth.egg-info/not-zip-safe
nap_token_auth.egg-info/requires.txt
nap_token_auth.egg-info/top_level.txt