Metadata-Version: 1.1
Name: nap-token-auth
Version: 0.1.2
Summary: A Minimal Token-Based Auth for Django
Home-page: http://github.com/funkybob/nap-token-auth/
Author: Curtis Maloney
Author-email: curtis@tinbrain.net
License: UNKNOWN
Keywords: django,token,auth,api
Platform: UNKNOWN
Classifier: Environment :: Web Environment
Classifier: Framework :: Django
Classifier: License :: OSI Approved :: BSD License
Classifier: Operating System :: OS Independent
Classifier: Programming Language :: Python
Classifier: Programming Language :: Python :: 3.5
Classifier: Programming Language :: Python :: 3.6
Requires: Django (>=1.8)
